<?xml version="1.0" encoding="UTF-8"?>
<equipment_list>
    <equipment name="Атаки" class="warrior,priest,rogue,archer,mage">
        <stat name="Броня">1795</stat>
        <stat name="Здоровье">835</stat>
        <stat name="Сопр. Крит">334</stat>
        <stat name="Восст. Здоровья">291</stat>
    </equipment>
    <equipment name="Быстроты" class="warrior,priest,rogue,archer,mage">
        <stat name="Здоровье">835</stat>
        <stat name="Скорость атаки">334</stat>
        <stat name="Точность">167</stat>
        <stat name="Восст. Энергии">102</stat>
    </equipment>
    <equipment name="Быстроты" class="warrior,priest,rogue,archer,mage">
        <stat name="Энергия">501</stat>
        <stat name="Скорость атаки">253</stat>
        <stat name="Точность">334</stat>
        <stat name="Уклонение">434</stat>
    </equipment>
    <equipment name="Жесткости" class="warrior,priest,rogue,archer,mage">
        <stat name="Маг. Броня">1795</stat>
        <stat name="Энергия">760</stat>
        <stat name="Сила атаки">300</stat>
        <stat name="Крит. Урон">167</stat>
    </equipment>
    <equipment name="Жесткости" class="warrior,priest,rogue,archer,mage">
        <stat name="Броня">1795</stat>
        <stat name="Сила атаки">300</stat>
        <stat name="Крит. Урон">253</stat>
        <stat name="Парирование">434</stat>
    </equipment>
    <equipment name="Изворотливости" class="warrior,priest,rogue,archer,mage">
        <stat name="Здоровье">835</stat>
        <stat name="Точность">167</stat>
        <stat name="Уклонение">868</stat>
        <stat name="Парирование">659</stat>
    </equipment>
    <equipment name="Контратаки" class="warrior,priest">
        <stat name="Маг. Броня">1795</stat>
        <stat name="Точность">167</stat>
        <stat name="Блок">253</stat>
        <stat name="Восст. Здоровья">383</stat>
    </equipment>
    <equipment name="Мастерства" class="warrior,priest">
        <stat name="Скорость атаки">167</stat>
        <stat name="Блок">253</stat>
        <stat name="Уклонение">434</stat>
        <stat name="Парирование">868</stat>
    </equipment>
    <equipment name="Неистовства" class="warrior,priest,rogue,archer,mage">
        <stat name="Энергия">501</stat>
        <stat name="Сила атаки">228</stat>
        <stat name="Скорость атаки">334</stat>
        <stat name="Крит. Урон">167</stat>
    </equipment>
    <equipment name="Ненависти" class="warrior,priest,rogue,archer,mage">
        <stat name="Сила атаки">150</stat>
        <stat name="Точность">167</stat>
        <stat name="Крит. Урон">334</stat>
        <stat name="Уклонение">659</stat>
    </equipment>
    <equipment name="Несгибаемости" class="warrior,priest">
        <stat name="Сопр. Магии">659</stat>
        <stat name="Блок">334</stat>
        <stat name="Уклонение">434</stat>
        <stat name="Восст. Энергии">67</stat>
    </equipment>
    <equipment name="Парирования" class="warrior,priest">
        <stat name="Броня">1795</stat>
        <stat name="Сопр.крит">253</stat>
        <stat name="Блок">167</stat>
        <stat name="Восст. Энергии">134</stat>
    </equipment>
    <equipment name="Свирепости" class="warrior,priest,rogue,archer,mage">
        <stat name="Скорость атаки">167</stat>
        <stat name="Крит. Урон">334</stat>
        <stat name="Уклонение">434</stat>
        <stat name="Парирование">659</stat>
    </equipment>
    <equipment name="Сопротивления" class="warrior,priest,rogue,archer,mage">
        <stat name="Маг. Броня">1795</stat>
        <stat name="Энергия">1002</stat>
        <stat name="Сопр. Магии">434</stat>
        <stat name="Восст. Энергии">102</stat>
    </equipment>
    <equipment name="Сопротивления" class="warrior,priest">
        <stat name="Здоровье">835</stat>
        <stat name="Сопр. Магии">659</stat>
        <stat name="Точность">167</stat>
        <stat name="Блок">334</stat>
    </equipment>
    <equipment name="Сопротивления" class="warrior,priest,rogue,archer,mage">
        <stat name="Маг. Броня">1795</stat>
        <stat name="Сопр. Магии">868</stat>
        <stat name="Уклонение">434</stat>
        <stat name="Восст. Здоровья">291</stat>
    </equipment>
    <equipment name="Стойкости" class="warrior,priest,rogue,archer,mage">
        <stat name="Маг. Броня">3591</stat>
        <stat name="Здоровье">1267</stat>
        <stat name="Уклонение">434</stat>
        <stat name="Восст. Здоровья">191</stat>
    </equipment>
    <equipment name="Стремительности" class="warrior,priest,rogue,archer,mage">
        <stat name="Здоровье">1669</stat>
        <stat name="Энергия">760</stat>
        <stat name="Крит. Урон">167</stat>
        <stat name="Восст. Энергии">67</stat>
    </equipment>
    <equipment name="Твердости" class="warrior,priest">
        <stat name="Здоровье">1669</stat>
        <stat name="Сопр. Магии">434</stat>
        <stat name="Сопр.крит">253</stat>
        <stat name="Блок">167</stat>
    </equipment>
    <equipment name="Уверенности" class="warrior,priest,rogue,archer,mage">
        <stat name="Броня">3591</stat>
        <stat name="Энергия">501</stat>
        <stat name="Сопр.крит">253</stat>
        <stat name="Крит. Урон">167</stat>
    </equipment>
    <equipment name="Удара" class="warrior,priest,rogue,archer,mage">
        <stat name="Скорость атаки">167</stat>
        <stat name="Точность">334</stat>
        <stat name="Крит. Урон">167</stat>
        <stat name="Уклонение">659</stat>
    </equipment>
    <equipment name="Устойчивости" class="warrior,priest,rogue,archer,mage">
        <stat name="Броня">3591</stat>
        <stat name="Маг. Броня">2726</stat>
        <stat name="Здоровье">835</stat>
        <stat name="Сопр.крит">86</stat>
    </equipment>
    <equipment name="Устойчивости" class="warrior,priest,rogue,archer,mage">
        <stat name="Броня">2726</stat>
        <stat name="Сопр. Магии">434</stat>
        <stat name="Скорость атаки">167</stat>
        <stat name="Сопр.крит">334</stat>
    </equipment>
    <equipment name="Фехтования" class="warrior,priest,rogue,archer,mage">
        <stat name="Маг. Броня">3591</stat>
        <stat name="Энергия">501</stat>
        <stat name="Сила атаки">228</stat>
        <stat name="Парирование">434</stat>
    </equipment>
</equipment_list>